setup.py
socketxio/__init__.py
socketxio/socketxio.py
socketxio.egg-info/PKG-INFO
socketxio.egg-info/SOURCES.txt
socketxio.egg-info/dependency_links.txt
socketxio.egg-info/top_level.txt