Metadata-Version: 1.2
Name: socketxio
Version: 1.7
Summary: A small example package made to help you with socket connections
Home-page: UNKNOWN
Author-email: none@example.com
License: UNKNOWN
Platform: UNKNOWN
Classifier: Programming Language :: Python :: 3
Classifier: License :: OSI Approved :: MIT License
Classifier: Operating System :: OS Independent
Requires-Python: >=3.6
